[
  {
    "item": "http://www.wikidata.org/entity/Q44039",
    "itemLabel": "Ludwig II of Bavaria",
    "positionLabel": "King of Bavaria",
    "sexLabel": "male",
    "year": "1864",
    "sitelinks": "72"
  },
  {
    "item": "http://www.wikidata.org/entity/Q44361",
    "itemLabel": "Ludwig I of Bavaria",
    "positionLabel": "King of Bavaria",
    "sexLabel": "male",
    "year": "1825",
    "sitelinks": "58"
  },
  {
    "item": "http://www.wikidata.org/entity/Q44319",
    "itemLabel": "Maximilian I Joseph of Bavaria",
    "positionLabel": "King of Bavaria",
    "sexLabel": "male",
    "year": "1806",
    "sitelinks": "53"
  },
  {
    "item": "http://www.wikidata.org/entity/Q44530",
    "itemLabel": "Maximilian II of Bavaria",
    "positionLabel": "King of Bavaria",
    "sexLabel": "male",
    "year": "1848",
    "sitelinks": "50"
  },
  {
    "item": "http://www.wikidata.org/entity/Q44393",
    "itemLabel": "Ludwig III of Bavaria",
    "positionLabel": "King of Bavaria",
    "sexLabel": "male",
    "year": "1913",
    "sitelinks": "47"
  },
  {
    "item": "http://www.wikidata.org/entity/Q44825",
    "itemLabel": "Otto, King of Bavaria",
    "positionLabel": "King of Bavaria",
    "sexLabel": "male",
    "year": "1886",
    "sitelinks": "44"
  }
]
