[
  {
    "qid": "Q174964",
    "title": "Charles IV of France becomes sovereign of Navarre",
    "subtitle": null,
    "year": 1322,
    "fact": "Charles IV, called the Fair in France and the Bald in Navarre, was the last king of the direct line of the House of Capet, King of France and King of Navarre from 1322 to 1328.",
    "wikipediaSlug": "Charles_IV_of_France",
    "image": "Charles4_mini.jpg",
    "pageViews": 10799
  },
  {
    "qid": "Q8384",
    "title": "Louis X of France becomes sovereign of Navarre",
    "subtitle": null,
    "year": 1305,
    "fact": "Louis X, known as the Quarrelsome, was King of France from 1314 and King of Navarre from 1305 until his death.",
    "wikipediaSlug": "Louis_X_of_France",
    "image": "Ludvík_X.png",
    "pageViews": 10780
  },
  {
    "qid": "Q8404",
    "title": "John I of France becomes sovereign of Navarre",
    "subtitle": null,
    "year": 1316,
    "fact": "John I, called the Posthumous, was the King of France and Navarre, as the posthumous son and successor of Louis X, for the four days he lived in 1316.",
    "wikipediaSlug": "John_I_of_France",
    "image": "JeanIposthume.JPG",
    "pageViews": 9157
  },
  {
    "qid": "Q8433",
    "title": "Philip V of France becomes sovereign of Navarre",
    "subtitle": null,
    "year": 1316,
    "fact": "Philip V, known as the Tall, was King of France and Navarre from 1316 to 1322.",
    "wikipediaSlug": "Philip_V_of_France",
    "image": "Sacre_Philippe5_France_01_(cropped).jpg",
    "pageViews": 8727
  },
  {
    "qid": "Q43082",
    "title": "Charles II of Navarre becomes sovereign of Navarre",
    "subtitle": null,
    "year": 1349,
    "fact": "Charles II, known as the Bad, was King of Navarre beginning in 1349, as well as Count of Évreux beginning in 1343, holding both titles until his death in 1387.",
    "wikipediaSlug": "Charles_II_of_Navarre",
    "image": "Charles_II_of_Navarre.png",
    "pageViews": 6470
  },
  {
    "qid": "Q229189",
    "title": "Joan I of Navarre becomes sovereign of Navarre",
    "subtitle": null,
    "year": 1284,
    "fact": "Joan I was ruling Queen of Navarre and Countess of Champagne from 1274 until 1305.",
    "wikipediaSlug": "Joan_I_of_Navarre",
    "image": "Joan_I_of_Navarre,_Queen_of_France_as_Benefactress,_from_a_portal_in_the_College_de_Navarre,_Paris,_c._1305,_limestone_-_Bode-Museum_-_DSC03464.JPG",
    "pageViews": 5893
  },
  {
    "qid": "Q230031",
    "title": "Joan II of Navarre becomes sovereign of Navarre",
    "subtitle": null,
    "year": 1328,
    "fact": "Joan II was Queen of Navarre from 1328 until her death in 1349.",
    "wikipediaSlug": "Joan_II_of_Navarre",
    "image": "Jana2Navarra_SaintDenis.jpg",
    "pageViews": 5050
  },
  {
    "qid": "Q312328",
    "title": "John II of Aragon becomes sovereign of Navarre",
    "subtitle": null,
    "year": 1464,
    "fact": "John II, called the Great or the Faithless, was King of Aragon from 1458 until his death in 1479.",
    "wikipediaSlug": "John_II_of_Aragon",
    "image": "SOAOTO_-_Folio_067R_(cropped).jpg",
    "pageViews": 4981
  },
  {
    "qid": "Q233865",
    "title": "Blanche I of Navarre becomes sovereign of Navarre",
    "subtitle": null,
    "year": 1425,
    "fact": "Blanche I was Queen of Navarre from the death of her father, King Charles III, in 1425 until her own death.",
    "wikipediaSlug": "Blanche_I_of_Navarre",
    "image": "Olite_-_Iglesia_de_Santa_María_la_Real,_atrio_4.jpg",
    "pageViews": 2640
  },
  {
    "qid": "Q318272",
    "title": "Sancho VII of Navarre becomes sovereign of Navarre",
    "subtitle": null,
    "year": 1194,
    "fact": "Sancho VII, called the Strong, was King of Navarre from 1194 until his death in 1234.",
    "wikipediaSlug": "Sancho_VII_of_Navarre",
    "image": "AntsoVIIArrano.JPG",
    "pageViews": 2639
  },
  {
    "qid": "Q236889",
    "title": "Leonor I of Navarre becomes sovereign of Navarre",
    "subtitle": null,
    "year": 1479,
    "fact": "Eleanor of Navarre was a Navarrese princess and monarch.",
    "wikipediaSlug": "Eleanor_of_Navarre",
    "image": "Royal_Coat_of_Arms_of_the_Crown_of_Castile_(15th_Century).svg",
    "pageViews": 2523
  },
  {
    "qid": "Q314562",
    "title": "Theobald I of Navarre becomes sovereign of Navarre",
    "subtitle": null,
    "year": 1234,
    "fact": "Theobald I, also called the Troubadour and the Posthumous, was Count of Champagne from birth and King of Navarre from 1234.",
    "wikipediaSlug": "Theobald_I_of_Navarre",
    "image": "Theobald_I_of_Navarre_2.jpg",
    "pageViews": 2515
  },
  {
    "qid": "Q236896",
    "title": "Catherine of Navarre becomes sovereign of Navarre",
    "subtitle": null,
    "year": 1483,
    "fact": "Catherine was Queen of Navarre from 1483 until 1517.",
    "wikipediaSlug": "Catherine_of_Navarre",
    "image": "Catherine_de_Foix.jpg",
    "pageViews": 2460
  },
  {
    "qid": "Q318258",
    "title": "Sancho VI of Navarre becomes sovereign of Navarre",
    "subtitle": null,
    "year": 1162,
    "fact": "Sancho Garcés VI, called the Wise was King of Navarre from 1150 until his death in 1194.",
    "wikipediaSlug": "Sancho_VI_of_Navarre",
    "image": "Sancho_VI_de_Navarra_-_Compendio_de_crónicas_de_reyes_(Biblioteca_Nacional_de_España).png",
    "pageViews": 2069
  },
  {
    "qid": "Q358365",
    "title": "Charles III of Navarre becomes sovereign of Navarre",
    "subtitle": null,
    "year": 1387,
    "fact": "Charles III, called the Noble, was King of Navarre from 1387 to his death and Count of Évreux in France from 1387 to 1404, when he exchanged Évreux for the Duchy of Nemours.",
    "wikipediaSlug": "Charles_III_of_Navarre",
    "image": "Karel3_Evreux_(cropped).jpg",
    "pageViews": 2047
  },
  {
    "qid": "Q366919",
    "title": "Henry I of Navarre becomes sovereign of Navarre",
    "subtitle": null,
    "year": 1271,
    "fact": "Henry the Fat was King of Navarre and Count of Champagne and Brie from 1270 until his death.",
    "wikipediaSlug": "Henry_I_of_Navarre",
    "image": "Henry_I_of_Nav.jpg",
    "pageViews": 1897
  },
  {
    "qid": "Q853282",
    "title": "Blanche II of Navarre becomes sovereign of Navarre",
    "subtitle": null,
    "year": 1461,
    "fact": "Blanche II was a Navarrese princess and claimant to the throne of Navarre.",
    "wikipediaSlug": "Blanche_II_of_Navarre",
    "image": "La_reina_Blanca_II_de_Navarra_(Museo_del_Prado).jpg",
    "pageViews": 1720
  },
  {
    "qid": "Q470641",
    "title": "Charles, Prince of Viana becomes sovereign of Navarre",
    "subtitle": null,
    "year": 1441,
    "fact": "Charles, Prince of Viana, sometimes called Charles IV of Navarre, was the eldest son of King John II of Aragon and Queen Blanche I of Navarre.",
    "wikipediaSlug": "Charles,_Prince_of_Viana",
    "image": "Princep_carles_de_viana.jpg",
    "pageViews": 1056
  }
]
