[
  {
    "qid": "Q28667972",
    "title": "‘One Piece’ is published",
    "subtitle": "Comic book by Eiichiro Oda",
    "year": 1997,
    "fact": "One Piece is a Japanese manga series written and illustrated by Eiichiro Oda.",
    "wikipediaSlug": "One_Piece",
    "image": "One_Piece,_Volume_61_Cover_(Japanese).jpg",
    "pageViews": 571342
  },
  {
    "qid": "Q55522899",
    "title": "‘Jujutsu Kaisen’ begins",
    "subtitle": "Japanese manga series",
    "year": 2018,
    "fact": "Jujutsu Kaisen is a Japanese manga series written and illustrated by Gege Akutami.",
    "wikipediaSlug": "Jujutsu_Kaisen",
    "image": "Jujutsu_kaisen.jpg",
    "pageViews": 301703
  },
  {
    "qid": "Q98642652",
    "title": "‘Frieren’ begins",
    "subtitle": "Japanese manga series",
    "year": 2020,
    "fact": "Frieren: Beyond Journey's End is a Japanese manga series written by Kanehito Yamada and illustrated by Tsukasa Abe.",
    "wikipediaSlug": "Frieren",
    "image": "Frieren_Beyond_Journey's_End.jpg",
    "pageViews": 213267
  },
  {
    "qid": "Q65240543",
    "title": "‘Chainsaw Man’ begins",
    "subtitle": "Japanese manga series",
    "year": 2018,
    "fact": "Chainsaw Man is a Japanese manga series written and illustrated by Tatsuki Fujimoto.",
    "wikipediaSlug": "Chainsaw_Man",
    "image": "Chainsawman.jpg",
    "pageViews": 189941
  },
  {
    "qid": "Q586025",
    "title": "‘Attack on Titan’ is published",
    "subtitle": "Comic book by Hajime Isayama",
    "year": 2009,
    "fact": "Attack on Titan is a Japanese manga series written and illustrated by Hajime Isayama.",
    "wikipediaSlug": "Attack_on_Titan",
    "image": "Shingeki_no_Kyojin_manga_volume_1.jpg",
    "pageViews": 164898
  },
  {
    "qid": "Q24862683",
    "title": "‘Demon Slayer: Kimetsu no Yaiba’ begins",
    "subtitle": "Japanese manga series",
    "year": 2016,
    "fact": "Demon Slayer: Kimetsu no Yaiba is a Japanese manga series written and illustrated by Koyoharu Gotouge.",
    "wikipediaSlug": "Demon_Slayer:_Kimetsu_no_Yaiba",
    "image": "Demon_Slayer_-_Kimetsu_no_Yaiba,_volume_1.jpg",
    "pageViews": 126839
  },
  {
    "qid": "Q26971382",
    "title": "‘Naruto’ begins",
    "subtitle": "Japanese manga series",
    "year": 1999,
    "fact": "Naruto is a Japanese manga series written and illustrated by Masashi Kishimoto.",
    "wikipediaSlug": "Naruto",
    "image": "NarutoCoverTankobon1.jpg",
    "pageViews": 124768
  },
  {
    "qid": "Q1834",
    "title": "‘Death Note’ begins",
    "subtitle": "Japanese manga series",
    "year": 2003,
    "fact": "Death Note is a Japanese manga series written by Tsugumi Ohba and illustrated by Takeshi Obata.",
    "wikipediaSlug": "Death_Note",
    "image": "Death_Note_Vol_1.jpg",
    "pageViews": 106830
  },
  {
    "qid": "Q97310775",
    "title": "‘Oshi no Ko’ begins",
    "subtitle": "Japanese manga series",
    "year": 2020,
    "fact": "Oshi no Ko (【推しの子】) is a Japanese manga series written by Aka Akasaka and illustrated by Mengo Yokoyari.",
    "wikipediaSlug": "Oshi_no_Ko",
    "image": "Oshi_no_Ko_Volume_1.jpg",
    "pageViews": 85771
  },
  {
    "qid": "Q18047903",
    "title": "‘My Hero Academia’ begins",
    "subtitle": "Japanese manga series",
    "year": 2014,
    "fact": "My Hero Academia is a Japanese manga series written and illustrated by Kōhei Horikoshi.",
    "wikipediaSlug": "My_Hero_Academia",
    "image": "Boku_no_Hero_Academia_Volume_1.png",
    "pageViews": 84280
  },
  {
    "qid": "Q18558978",
    "title": "‘Berserk’ begins",
    "subtitle": "Japanese manga series",
    "year": 1989,
    "fact": "Berserk is a Japanese manga series created by Kentaro Miura.",
    "wikipediaSlug": "Berserk_(manga)",
    "image": "Berserk_vol01.png",
    "pageViews": 82228
  },
  {
    "qid": "Q696071",
    "title": "‘Hunter × Hunter’ begins",
    "subtitle": "Japanese manga series",
    "year": 1998,
    "fact": "Hunter × Hunter is a Japanese manga series written and illustrated by Yoshihiro Togashi.",
    "wikipediaSlug": "Hunter_%C3%97_Hunter",
    "image": "Hunter_×_Hunter_vol._1.png",
    "pageViews": 77779
  },
  {
    "qid": "Q30924292",
    "title": "‘Beastars’ begins",
    "subtitle": "Japanese manga series",
    "year": 2016,
    "fact": "Beastars is a Japanese manga series written and illustrated by Paru Itagaki.",
    "wikipediaSlug": "Beastars",
    "image": "BEASTARS,_volume_1.jpg",
    "pageViews": 74921
  },
  {
    "qid": "Q20016948",
    "title": "‘Delicious in Dungeon’ begins",
    "subtitle": "Japanese manga series",
    "year": 2015,
    "fact": "Delicious in Dungeon, is a Japanese manga series written and illustrated by Ryoko Kui.",
    "wikipediaSlug": "Delicious_in_Dungeon",
    "image": "Dungeon_Meshi_cover.jpeg",
    "pageViews": 74742
  },
  {
    "qid": "Q235311",
    "title": "‘Doraemon’ is published",
    "subtitle": "Comic book by Fujiko F. Fujio",
    "year": 1969,
    "fact": "Doraemon (ドラえもん) is a Japanese manga series written and illustrated by Fujiko F.",
    "wikipediaSlug": "Doraemon",
    "image": "Doraemon_volume_1_cover.jpg",
    "pageViews": 64332
  },
  {
    "qid": "Q1643098",
    "title": "‘Sailor Moon’ is published",
    "subtitle": "Comic book by Naoko Takeuchi",
    "year": 1991,
    "fact": "Sailor Moon is a Japanese manga series written and illustrated by Naoko Takeuchi.",
    "wikipediaSlug": "Sailor_Moon",
    "image": "SMVolume1.jpg",
    "pageViews": 61614
  },
  {
    "qid": "Q65231576",
    "title": "‘Spy × Family’ begins",
    "subtitle": "Japanese manga series",
    "year": 2019,
    "fact": "Spy × Family is a Japanese web manga series written and illustrated by Tatsuya Endo.",
    "wikipediaSlug": "Spy_%C3%97_Family",
    "image": "Spy_Family_vol_1.jpg",
    "pageViews": 60015
  },
  {
    "qid": "Q108069627",
    "title": "‘Dandadan’ begins",
    "subtitle": "Japanese manga series",
    "year": 2021,
    "fact": "Dandadan (ダンダダン), also written as Dan Da Dan, is a Japanese web manga series writen and illustrated by Yukinobu Tatsu.",
    "wikipediaSlug": "Dandadan",
    "image": "Dandadan_vol._1_cover.jpg",
    "pageViews": 59810
  },
  {
    "qid": "Q189562",
    "title": "‘Fullmetal Alchemist’ is published",
    "subtitle": "Comic book by Hiromu Arakawa",
    "year": 2001,
    "fact": "Fullmetal Alchemist is a Japanese manga series written and illustrated by Hiromu Arakawa.",
    "wikipediaSlug": "Fullmetal_Alchemist",
    "image": "Fullmetal123.jpg",
    "pageViews": 57967
  },
  {
    "qid": "Q744536",
    "title": "‘The Adventures of Tintin’ begins",
    "subtitle": "Series of 24 comic albums by Belgian cartoonist Georges Remi",
    "year": 1929,
    "fact": "The Adventures of Tintin is a series of 24 comic albums created by Belgian cartoonist Hergé.",
    "wikipediaSlug": "The_Adventures_of_Tintin",
    "image": "Tintin-mainCast.png",
    "pageViews": 56118
  },
  {
    "qid": "Q20638503",
    "title": "‘Black Clover’ begins",
    "subtitle": "Japanese manga series",
    "year": 2015,
    "fact": "Black Clover is a Japanese manga series written and illustrated by Yūki Tabata.",
    "wikipediaSlug": "Black_Clover",
    "image": "Black_Clover,_volume_1.jpg",
    "pageViews": 50282
  },
  {
    "qid": "Q65235036",
    "title": "‘My Dress-Up Darling’ begins",
    "subtitle": "Japanese manga series",
    "year": 2018,
    "fact": "My Dress-Up Darling is a Japanese manga series written and illustrated by Shinichi Fukuda.",
    "wikipediaSlug": "My_Dress-Up_Darling",
    "image": "Sono_Bisque_Doll_wa_Koi_wo_Suru,_Volume_1.jpg",
    "pageViews": 49623
  },
  {
    "qid": "Q11419997",
    "title": "‘Your Lie in April’ begins",
    "subtitle": "Japanese manga series",
    "year": 2011,
    "fact": "Your Lie in April is a Japanese romantic drama manga series written and illustrated by Naoshi Arakawa.",
    "wikipediaSlug": "Your_Lie_in_April",
    "image": "Your_Lie_in_April_Manga_cover.png",
    "pageViews": 45540
  },
  {
    "qid": "Q42490",
    "title": "‘Asterix’ begins",
    "subtitle": "Series of French comic books",
    "year": 1959,
    "fact": "Asterix is a French comic album series about a Gaulish village which, thanks to a magic potion that enhances strength, resists the forces of Julius Caesar's Roman Republic Army in the time after the Gallic Wars.",
    "wikipediaSlug": "Asterix",
    "image": "Asterix.svg",
    "pageViews": 45432
  },
  {
    "qid": "Q18335422",
    "title": "‘Made in Abyss’ begins",
    "subtitle": "Japanese manga series",
    "year": 2012,
    "fact": "Made in Abyss is a Japanese web manga series written and illustrated by Akihito Tsukushi.",
    "wikipediaSlug": "Made_in_Abyss",
    "image": "Made_in_Abyss_volume_1_cover.jpg",
    "pageViews": 44045
  },
  {
    "qid": "Q62414782",
    "title": "‘Blue Lock’ begins",
    "subtitle": "Japanese manga series",
    "year": 2018,
    "fact": "Blue Lock is a Japanese manga series written by Muneyuki Kaneshiro and illustrated by Yusuke Nomura.",
    "wikipediaSlug": "Blue_Lock",
    "image": "Blue_Lock_manga_volume_1.png",
    "pageViews": 43124
  },
  {
    "qid": "Q120300",
    "title": "‘Crayon Shin-chan’ begins",
    "subtitle": "Japanese manga series",
    "year": 1990,
    "fact": "Crayon Shin-chan is a Japanese manga series written and illustrated by Yoshito Usui.",
    "wikipediaSlug": "Crayon_Shin-chan",
    "image": "Crayon_Shin-chan_vol_1_cover.jpg",
    "pageViews": 42895
  },
  {
    "qid": "Q858384",
    "title": "‘Monster’ begins",
    "subtitle": "Japanese manga series",
    "year": 1994,
    "fact": "Monster is a Japanese manga series written and illustrated by Naoki Urasawa.",
    "wikipediaSlug": "Monster_(manga)",
    "image": "Monster_manga_volume_1_cover.jpg",
    "pageViews": 41246
  },
  {
    "qid": "Q11102941",
    "title": "‘Tokyo Ghoul’ begins",
    "subtitle": "Japanese manga series",
    "year": 2011,
    "fact": "Tokyo Ghoul is a Japanese dark fantasy manga series written and illustrated by Sui Ishida.",
    "wikipediaSlug": "Tokyo_Ghoul",
    "image": "Tokyo_Ghoul_volume_1_cover.jpg",
    "pageViews": 41214
  },
  {
    "qid": "Q326642",
    "title": "‘Haikyu!!’ begins",
    "subtitle": "Japanese manga series",
    "year": 2012,
    "fact": "Haikyu!!",
    "wikipediaSlug": "Haikyu!!",
    "image": "Haikyū_Volume_1.jpg",
    "pageViews": 40563
  },
  {
    "qid": "Q715193",
    "title": "‘Hajime no Ippo’ begins",
    "subtitle": "Japanese manga series",
    "year": 1989,
    "fact": "Hajime no Ippo is a Japanese boxing-themed manga series written and illustrated by George Morikawa.",
    "wikipediaSlug": "Hajime_no_Ippo",
    "image": "Hajime_no_Ippo_1.png",
    "pageViews": 40356
  },
  {
    "qid": "Q128444",
    "title": "‘Watchmen’ is published",
    "subtitle": "Comic book by Alan Moore",
    "year": 1986,
    "fact": "Watchmen is a comic book limited series by the British creative team of writer Alan Moore, artist Dave Gibbons, and colorist John Higgins.",
    "wikipediaSlug": "Watchmen",
    "image": "Watchmen,_issue_1.jpg",
    "pageViews": 40012
  },
  {
    "qid": "Q28682687",
    "title": "‘The Promised Neverland’ begins",
    "subtitle": "Japanese manga series",
    "year": 2016,
    "fact": "The Promised Neverland is a Japanese manga series written by Kaiu Shirai and illustrated by Posuka Demizu.",
    "wikipediaSlug": "The_Promised_Neverland",
    "image": "The_Promised_Neverland,_Volume_1.jpg",
    "pageViews": 39660
  },
  {
    "qid": "Q63981675",
    "title": "‘Tokyo Revengers’ begins",
    "subtitle": "Japanese manga series",
    "year": 2017,
    "fact": "Tokyo Revengers is a Japanese manga series written and illustrated by Ken Wakui.",
    "wikipediaSlug": "Tokyo_Revengers",
    "image": "Tokyo_Revengers_volume_1_cover.jpg",
    "pageViews": 39116
  },
  {
    "qid": "Q537389",
    "title": "‘Soul Eater’ begins",
    "subtitle": "Japanese manga series",
    "year": 2004,
    "fact": "Soul Eater is a Japanese manga series written and illustrated by Atsushi Ohkubo.",
    "wikipediaSlug": "Soul_Eater",
    "image": "Soul_Eater_manga_volume_1.jpg",
    "pageViews": 39063
  },
  {
    "qid": "Q930990",
    "title": "‘Vinland Saga’ begins",
    "subtitle": "Japanese manga series",
    "year": 2005,
    "fact": "Vinland Saga is a Japanese manga series written and illustrated by Makoto Yukimura.",
    "wikipediaSlug": "Vinland_Saga_(manga)",
    "image": "Vinland_Saga_volume_01_cover.jpg",
    "pageViews": 38611
  },
  {
    "qid": "Q3853685",
    "title": "‘Detective Conan’ begins",
    "subtitle": "Japanese manga series",
    "year": 1994,
    "fact": "Case Closed, also officially known as Detective Conan, is a Japanese manga series written and illustrated by Gosho Aoyama.",
    "wikipediaSlug": "Case_Closed",
    "image": "Case_Closed_Volume_36.png",
    "pageViews": 38503
  },
  {
    "qid": "Q164883",
    "title": "‘Initial D’ begins",
    "subtitle": "Japanese manga series",
    "year": 1995,
    "fact": "Initial D is a Japanese street racing manga series written and illustrated by Shuichi Shigeno.",
    "wikipediaSlug": "Initial_D",
    "image": "InitialD_vol1_Cover.jpg",
    "pageViews": 37674
  },
  {
    "qid": "Q18225473",
    "title": "‘Yu Yu Hakusho’ begins",
    "subtitle": "Japanese manga series",
    "year": 1990,
    "fact": "YuYu Hakusho is a Japanese manga series written and illustrated by Yoshihiro Togashi.",
    "wikipediaSlug": "YuYu_Hakusho",
    "image": "YuYu_Hakusho_1.png",
    "pageViews": 37188
  },
  {
    "qid": "Q72533",
    "title": "‘Garfield’ is published",
    "subtitle": "Comic book by Jim Davis",
    "year": 1978,
    "fact": "Garfield is an American comic strip created by Jim Davis.",
    "wikipediaSlug": "Garfield",
    "image": "Garfieldand_friends.png",
    "pageViews": 36049
  },
  {
    "qid": "Q272015",
    "title": "‘Ranma ½’ begins",
    "subtitle": "Japanese manga series",
    "year": 1987,
    "fact": "Ranma ½ is a Japanese manga series written and illustrated by Rumiko Takahashi.",
    "wikipediaSlug": "Ranma_%C2%BD",
    "image": "Ranma1_2volume1.jpg",
    "pageViews": 35446
  },
  {
    "qid": "Q38275959",
    "title": "‘Dr. Stone’ begins",
    "subtitle": "Japanese manga series",
    "year": 2017,
    "fact": "Dr.",
    "wikipediaSlug": "Dr._Stone",
    "image": "Doctor_stone.jpg",
    "pageViews": 34519
  },
  {
    "qid": "Q182056",
    "title": "‘Inuyasha’ begins",
    "subtitle": "Japanese manga series",
    "year": 1996,
    "fact": "Inuyasha is a Japanese manga series written and illustrated by Rumiko Takahashi.",
    "wikipediaSlug": "Inuyasha",
    "image": "Inuyasha_1.png",
    "pageViews": 34389
  },
  {
    "qid": "Q423658",
    "title": "‘Nana’ begins",
    "subtitle": "Japanese manga series",
    "year": 2000,
    "fact": "Nana is a Japanese manga series written and illustrated by Ai Yazawa.",
    "wikipediaSlug": "Nana_(manga)",
    "image": "Nana_volume_1.png",
    "pageViews": 33032
  },
  {
    "qid": "Q733498",
    "title": "‘Fist of the North Star’ begins",
    "subtitle": "Japanese manga series",
    "year": 1983,
    "fact": "Fist of the North Star is a Japanese manga series written by Buronson and illustrated by Tetsuo Hara.",
    "wikipediaSlug": "Fist_of_the_North_Star",
    "image": "Fist_of_the_North_Star_1.png",
    "pageViews": 32746
  },
  {
    "qid": "Q211035",
    "title": "‘Calvin and Hobbes’ begins",
    "subtitle": "Comic strip by Bill Watterson",
    "year": 1985,
    "fact": "Calvin and Hobbes is a daily American comic strip created by cartoonist Bill Watterson that was syndicated from November 18, 1985, to December 31, 1995.",
    "wikipediaSlug": "Calvin_and_Hobbes",
    "image": "Calvin_and_Hobbes_Original.png",
    "pageViews": 32688
  },
  {
    "qid": "Q308035",
    "title": "‘XXholic xxx’ begins",
    "subtitle": "Japanese manga series",
    "year": 2003,
    "fact": "xxxHolic is a Japanese manga series written and illustrated by the manga group Clamp.",
    "wikipediaSlug": "XxxHolic",
    "image": "XxxHolic_vol1_Cover.jpg",
    "pageViews": 31973
  },
  {
    "qid": "Q18796",
    "title": "‘Fairy Tail’ begins",
    "subtitle": "Japanese manga series",
    "year": 2006,
    "fact": "Fairy Tail is a Japanese manga series written and illustrated by Hiro Mashima.",
    "wikipediaSlug": "Fairy_Tail",
    "image": "FairyTail-Volume_1_Cover.jpg",
    "pageViews": 31956
  },
  {
    "qid": "Q103411",
    "title": "‘V for Vendetta’ begins",
    "subtitle": "Graphic novel by Alan Moore and David Lloyd",
    "year": 1980,
    "fact": "V for Vendetta is a British graphic novel written by Alan Moore and illustrated by David Lloyd.",
    "wikipediaSlug": "V_for_Vendetta",
    "image": "V_for_vendettax.jpg",
    "pageViews": 31907
  },
  {
    "qid": "Q55695988",
    "title": "‘Rent-A-Girlfriend’ begins",
    "subtitle": "Japanese manga series",
    "year": 2017,
    "fact": "Rent-A-Girlfriend, abbreviated in Japan as Kanokari (かのかり), is a Japanese manga series written and illustrated by Reiji Miyajima.",
    "wikipediaSlug": "Rent-A-Girlfriend",
    "image": "Rent-A-Girlfriend_volume_1_cover.jpg",
    "pageViews": 31605
  },
  {
    "qid": "Q827099",
    "title": "‘The Sandman’ begins",
    "subtitle": "Comic series by Neil Gaiman",
    "year": 1988,
    "fact": "The Sandman is a dark fantasy comic book series written by Neil Gaiman and published by DC Comics.",
    "wikipediaSlug": "The_Sandman_(comic_book)",
    "image": "Sandman_no.1_(Modern_Age).comiccover.jpg",
    "pageViews": 30165
  },
  {
    "qid": "Q340181",
    "title": "‘The Walking Dead’ begins",
    "subtitle": "Comic book series by Robert Kirkman, Tony Moore and Charlie Adlard",
    "year": 2003,
    "fact": "The Walking Dead is an American zombie apocalypse comic book series created by writer Robert Kirkman and artist Tony Moore – who was the artist on the first six issues and cover artist for the first twenty-four – with art on the remainder of the series by Charlie Adlard.",
    "wikipediaSlug": "The_Walking_Dead_(comic_book)",
    "image": "WalkingDead1.jpg",
    "pageViews": 29160
  },
  {
    "qid": "Q137475",
    "title": "‘Lucky Luke’ begins",
    "subtitle": "Belgian comics series by Morris",
    "year": 1946,
    "fact": "Lucky Luke is a Western comic album series created by Belgian cartoonist Morris in 1946.",
    "wikipediaSlug": "Lucky_Luke",
    "image": "LuckyLuke2.png",
    "pageViews": 29002
  },
  {
    "qid": "Q673036",
    "title": "‘Astro Boy’ begins",
    "subtitle": "Japanese manga series",
    "year": 1952,
    "fact": "Astro Boy, known in Japan as Mighty Atom, is a Japanese manga series written and illustrated by Osamu Tezuka.",
    "wikipediaSlug": "Astro_Boy",
    "image": "Astro_Boy-08.jpg",
    "pageViews": 27752
  },
  {
    "qid": "Q9048543",
    "title": "‘The Seven Deadly Sins’ begins",
    "subtitle": "Japanese manga series",
    "year": 2012,
    "fact": "The Seven Deadly Sins is a Japanese fantasy manga series written and illustrated by Nakaba Suzuki.",
    "wikipediaSlug": "The_Seven_Deadly_Sins_(manga)",
    "image": "Nanatsu_no_Taizai_Volume_1.png",
    "pageViews": 27692
  },
  {
    "qid": "Q327773",
    "title": "‘Ouran High School Host Club’ begins",
    "subtitle": "Japanese manga series",
    "year": 2002,
    "fact": "Ouran High School Host Club is a Japanese romantic comedy manga series written and illustrated by Bisco Hatori.",
    "wikipediaSlug": "Ouran_High_School_Host_Club",
    "image": "Ouran_High_School_Vol_1_cover.jpg",
    "pageViews": 26856
  },
  {
    "qid": "Q49182",
    "title": "‘Cardcaptor Sakura’ begins",
    "subtitle": "Japanese manga series",
    "year": 1996,
    "fact": "Cardcaptor Sakura, abbreviated as CCS, is a Japanese manga series written and illustrated by the manga group Clamp.",
    "wikipediaSlug": "Cardcaptor_Sakura",
    "image": "Cardcaptor_Sakura_vol1_cover.jpg",
    "pageViews": 24489
  },
  {
    "qid": "Q3277067",
    "title": "‘Assassination Classroom’ begins",
    "subtitle": "Japanese manga series",
    "year": 2012,
    "fact": "Assassination Classroom is a Japanese manga series written and illustrated by Yusei Matsui.",
    "wikipediaSlug": "Assassination_Classroom",
    "image": "Assassination_Classroom_Volume_1.jpg",
    "pageViews": 24047
  },
  {
    "qid": "Q1525793",
    "title": "‘Akame ga Kill!’ begins",
    "subtitle": "Japanese manga series",
    "year": 2010,
    "fact": "Akame ga Kill!",
    "wikipediaSlug": "Akame_ga_Kill!",
    "image": "Akame_ga_Kill_volume_1_cover.jpg",
    "pageViews": 24030
  },
  {
    "qid": "Q223155",
    "title": "‘Hellsing’ begins",
    "subtitle": "Japanese manga series",
    "year": 1997,
    "fact": "Hellsing is a Japanese manga series written and illustrated by Kouta Hirano.",
    "wikipediaSlug": "Hellsing",
    "image": "Hellsing_1.png",
    "pageViews": 23686
  },
  {
    "qid": "Q696302",
    "title": "‘Black Butler’ begins",
    "subtitle": "Japanese manga series",
    "year": 2006,
    "fact": "Black Butler is a Japanese manga series written and illustrated by Yana Toboso.",
    "wikipediaSlug": "Black_Butler",
    "image": "Black_Butler_1.png",
    "pageViews": 23462
  },
  {
    "qid": "Q714760",
    "title": "‘Slam Dunk’ begins",
    "subtitle": "Japanese manga series",
    "year": 1990,
    "fact": "Slam Dunk is a Japanese sports manga series written and illustrated by Takehiko Inoue.",
    "wikipediaSlug": "Slam_Dunk_(manga)",
    "image": "Slam_Dunk_(manga)_1.png",
    "pageViews": 23296
  },
  {
    "qid": "Q214771",
    "title": "‘Elfen Lied’ begins",
    "subtitle": "Japanese manga series",
    "year": 2002,
    "fact": "Elfen Lied is a Japanese manga series written and illustrated by Lynn Okamoto.",
    "wikipediaSlug": "Elfen_Lied",
    "image": "Elfen_Lied_manga_volume_1.jpg",
    "pageViews": 21682
  },
  {
    "qid": "Q216204",
    "title": "‘Fruits Basket’ begins",
    "subtitle": "Japanese manga series",
    "year": 1998,
    "fact": "Fruits Basket, sometimes abbreviated Furuba or Fruba (フルバ), is a Japanese manga series written and illustrated by Natsuki Takaya.",
    "wikipediaSlug": "Fruits_Basket",
    "image": "Fruits_Basket_manga.jpg",
    "pageViews": 21440
  },
  {
    "qid": "Q275956",
    "title": "‘Saint Seiya’ begins",
    "subtitle": "Japanese manga series",
    "year": 1986,
    "fact": "Saint Seiya, also known as Saint Seiya: Knights of the Zodiac or simply Knights of the Zodiac, is a Japanese manga series written and illustrated by Masami Kurumada.",
    "wikipediaSlug": "Saint_Seiya",
    "image": "Saint_Seiya_1.png",
    "pageViews": 21211
  },
  {
    "qid": "Q38277250",
    "title": "‘The Quintessential Quintuplets’ begins",
    "subtitle": "Japanese manga series",
    "year": 2017,
    "fact": "The Quintessential Quintuplets is a Japanese manga series written and illustrated by Negi Haruba.",
    "wikipediaSlug": "The_Quintessential_Quintuplets",
    "image": "The_Quintessential_Quintuplets_volume_1_cover.jpg",
    "pageViews": 20979
  },
  {
    "qid": "Q423652",
    "title": "‘Black Lagoon’ begins",
    "subtitle": "Japanese manga series",
    "year": 2002,
    "fact": "Black Lagoon is a Japanese manga series written and illustrated by Rei Hiroe.",
    "wikipediaSlug": "Black_Lagoon",
    "image": "Black_Lagoon_01.png",
    "pageViews": 20851
  },
  {
    "qid": "Q80873",
    "title": "‘Azumanga Daioh’ begins",
    "subtitle": "Japanese manga series",
    "year": 1999,
    "fact": "Azumanga Daioh is a Japanese yonkoma comedy manga series written and illustrated by Kiyohiko Azuma.",
    "wikipediaSlug": "Azumanga_Daioh",
    "image": "AzumangaDaioh-vol1cover-jp.jpg",
    "pageViews": 19347
  },
  {
    "qid": "Q495919",
    "title": "‘Blue Exorcist’ begins",
    "subtitle": "Japanese manga series",
    "year": 2009,
    "fact": "Blue Exorcist is a Japanese manga series written and illustrated by Kazue Kato.",
    "wikipediaSlug": "Blue_Exorcist",
    "image": "Blue_Exorcist_vol_1.png",
    "pageViews": 18779
  },
  {
    "qid": "Q457981",
    "title": "‘Great Teacher Onizuka’ begins",
    "subtitle": "Japanese manga series",
    "year": 1997,
    "fact": "Great Teacher Onizuka, abbreviated as GTO, is a Japanese manga series written and illustrated by Tooru Fujisawa.",
    "wikipediaSlug": "Great_Teacher_Onizuka",
    "image": "GTO_volume_1.jpg",
    "pageViews": 18173
  },
  {
    "qid": "Q715723",
    "title": "‘Urusei Yatsura’ begins",
    "subtitle": "Japanese manga series",
    "year": 1978,
    "fact": "Urusei Yatsura (うる星やつら) is a Japanese manga series written and illustrated by Rumiko Takahashi.",
    "wikipediaSlug": "Urusei_Yatsura",
    "image": "Urusei_Yatsura_volume_1_tankobon_cover.jpg",
    "pageViews": 17810
  },
  {
    "qid": "Q11606274",
    "title": "‘Seraph of the End’ begins",
    "subtitle": "Japanese manga series",
    "year": 2012,
    "fact": "Seraph of the End is a Japanese dark fantasy manga series.",
    "wikipediaSlug": "Seraph_of_the_End",
    "image": "Seraph_of_the_End.jpg",
    "pageViews": 17721
  },
  {
    "qid": "Q830771",
    "title": "‘Highschool of the Dead’ begins",
    "subtitle": "Japanese manga series",
    "year": 2006,
    "fact": "Highschool of the Dead, known in Japan as Apocalyptic Academy: Highschool of the Dead, is a Japanese manga series written by Daisuke Satō and illustrated by Shōji Satō.",
    "wikipediaSlug": "Highschool_of_the_Dead",
    "image": "Highschool_of_the_Dead_volume_1.png",
    "pageViews": 17419
  },
  {
    "qid": "Q945730",
    "title": "‘Parasyte’ begins",
    "subtitle": "Japanese manga series",
    "year": 1989,
    "fact": "Parasyte is a Japanese science fiction horror manga series written and illustrated by Hitoshi Iwaaki.",
    "wikipediaSlug": "Parasyte",
    "image": "Parasyte_4.png",
    "pageViews": 17058
  },
  {
    "qid": "Q91486",
    "title": "‘Akira’ begins",
    "subtitle": "Manga series by Katsuhiro Otomo",
    "year": 1988,
    "fact": "Akira is a Japanese cyberpunk post-apocalyptic manga series written and illustrated by Katsuhiro Otomo.",
    "wikipediaSlug": "Akira_(manga)",
    "image": "Akira_Volume_1_Cover_Japanese_Version_(Manga).jpg",
    "pageViews": 17036
  },
  {
    "qid": "Q482715",
    "title": "‘Kuroko's Basketball’ begins",
    "subtitle": "Japanese manga series",
    "year": 2009,
    "fact": "Kuroko's Basketball is a Japanese sports manga series written and illustrated by Tadatoshi Fujimaki.",
    "wikipediaSlug": "Kuroko%27s_Basketball",
    "image": "Kuroko_no_Basuke_Cover.jpg",
    "pageViews": 16932
  },
  {
    "qid": "Q1057617",
    "title": "‘Gantz’ begins",
    "subtitle": "Japanese manga series",
    "year": 2000,
    "fact": "Gantz is a Japanese manga series written and illustrated by Hiroya Oku.",
    "wikipediaSlug": "Gantz",
    "image": "Gantz_vol._1.png",
    "pageViews": 16725
  },
  {
    "qid": "Q11377464",
    "title": "‘Alice in Borderland’ begins",
    "subtitle": "Japanese manga series",
    "year": 2010,
    "fact": "Alice in Borderland is a Japanese manga series written and illustrated by Haro Aso.",
    "wikipediaSlug": "Alice_in_Borderland",
    "image": "Alice_in_Borderland_cover.jpeg",
    "pageViews": 16410
  },
  {
    "qid": "Q494357",
    "title": "‘Future Diary’ begins",
    "subtitle": "Japanese manga series",
    "year": 2006,
    "fact": "Future Diary is a Japanese manga series written and illustrated by Sakae Esuno.",
    "wikipediaSlug": "Future_Diary",
    "image": "Mirainikkicover.jpg",
    "pageViews": 16231
  },
  {
    "qid": "Q482482",
    "title": "‘K-On!’ begins",
    "subtitle": "Japanese manga series",
    "year": 2007,
    "fact": "K-On!",
    "wikipediaSlug": "K-On!",
    "image": "K-On!_manga_volume_1_cover.jpg",
    "pageViews": 15963
  },
  {
    "qid": "Q699631",
    "title": "‘The Rose of Versailles’ begins",
    "subtitle": "Japanese manga series",
    "year": 1972,
    "fact": "The Rose of Versailles, also known as Lady Oscar and La Rose de Versailles, is a Japanese manga series written and illustrated by Riyoko Ikeda.",
    "wikipediaSlug": "The_Rose_of_Versailles",
    "image": "The_Rose_of_Versailles_Volume_1.png",
    "pageViews": 15900
  },
  {
    "qid": "Q726431",
    "title": "‘Dilbert’ begins",
    "subtitle": "American comic strip",
    "year": 1989,
    "fact": "Dilbert is an American comic strip which was written and illustrated by Scott Adams, first published on April 16, 1989.",
    "wikipediaSlug": "Dilbert",
    "image": "Dilbert-20050910.png",
    "pageViews": 15721
  },
  {
    "qid": "Q22123892",
    "title": "‘Cells at Work!’ begins",
    "subtitle": "Japanese manga series",
    "year": 2015,
    "fact": "Cells at Work!",
    "wikipediaSlug": "Cells_at_Work!",
    "image": "Cells_at_Work_v1_cover.jpg",
    "pageViews": 14341
  },
  {
    "qid": "Q13915",
    "title": "‘Xkcd’ begins",
    "subtitle": "Webcomic created by Randall Munroe",
    "year": 2005,
    "fact": "xkcd is a serial webcomic created in 2005 by American author Randall Munroe.",
    "wikipediaSlug": "Xkcd",
    "image": "Xkcd_philosophy.png",
    "pageViews": 14225
  },
  {
    "qid": "Q714064",
    "title": "‘City Hunter’ begins",
    "subtitle": "Japanese manga series",
    "year": 1985,
    "fact": "City Hunter is a Japanese manga series written and illustrated by Tsukasa Hojo.",
    "wikipediaSlug": "City_Hunter",
    "image": "City_Hunter_1.png",
    "pageViews": 14077
  },
  {
    "qid": "Q1055370",
    "title": "‘Mushishi’ begins",
    "subtitle": "Japanese manga series",
    "year": 1999,
    "fact": "Mushishi is a Japanese manga series written and illustrated by Yuki Urushibara.",
    "wikipediaSlug": "Mushishi",
    "image": "Mushishi,_Volume_1.jpg",
    "pageViews": 14038
  },
  {
    "qid": "Q11147846",
    "title": "‘Noragami’ begins",
    "subtitle": "Japanese manga series",
    "year": 2010,
    "fact": "Noragami: Stray God is a Japanese manga series written and illustrated by the manga artist duo Adachitoka.",
    "wikipediaSlug": "Noragami",
    "image": "Noragami_1.png",
    "pageViews": 13772
  },
  {
    "qid": "Q170019",
    "title": "‘D.Gray-man’ begins",
    "subtitle": "Japanese manga series",
    "year": 2004,
    "fact": "D.Gray-man is a Japanese manga series written and illustrated by Katsura Hoshino.",
    "wikipediaSlug": "D.Gray-man",
    "image": "D.Gray-man_1.png",
    "pageViews": 13740
  },
  {
    "qid": "Q810987",
    "title": "‘Battle Angel Alita’ begins",
    "subtitle": "Japanese manga series",
    "year": 1990,
    "fact": "Battle Angel Alita, known in Japan as Gunnm, is a Japanese cyberpunk manga series created by Yukito Kishiro and originally published in Shueisha's Business Jump magazine from 1990 to 1995.",
    "wikipediaSlug": "Battle_Angel_Alita",
    "image": "Battle_Angel_Alita_vol01.jpg",
    "pageViews": 13537
  },
  {
    "qid": "Q701050",
    "title": "‘Chibi Maruko-chan’ begins",
    "subtitle": "Japanese manga series",
    "year": 1986,
    "fact": "Chibi Maruko-chan is a manga series written and illustrated by Momoko Sakura.",
    "wikipediaSlug": "Chibi_Maruko-chan",
    "image": "Chibi_maruko-chan_comic_no_1_cover.jpg",
    "pageViews": 12878
  },
  {
    "qid": "Q839091",
    "title": "‘Lucky Star’ begins",
    "subtitle": "Japanese manga series",
    "year": 2003,
    "fact": "Lucky Star is a Japanese four-panel comic strip manga series by Kagami Yoshimizu.",
    "wikipediaSlug": "Lucky_Star_(manga)",
    "image": "Lucky_Star_vol_1_manga_cover.jpg",
    "pageViews": 12870
  },
  {
    "qid": "Q219610",
    "title": "‘Shaman King’ begins",
    "subtitle": "Japanese manga series",
    "year": 1998,
    "fact": "Shaman King is a Japanese manga series written and illustrated by Hiroyuki Takei.",
    "wikipediaSlug": "Shaman_King",
    "image": "Shaman_King_vol._32.png",
    "pageViews": 12741
  },
  {
    "qid": "Q761921",
    "title": "‘Magi: The Labyrinth of Magic’ begins",
    "subtitle": "Japanese manga series",
    "year": 2009,
    "fact": "Magi: The Labyrinth of Magic is a Japanese manga series written and illustrated by Shinobu Ohtaka.",
    "wikipediaSlug": "Magi:_The_Labyrinth_of_Magic",
    "image": "MagiCover01.png",
    "pageViews": 12272
  },
  {
    "qid": "Q476230",
    "title": "‘Claymore’ begins",
    "subtitle": "Japanese manga series",
    "year": 2007,
    "fact": "Claymore is a Japanese dark fantasy manga series written and illustrated by Norihiro Yagi.",
    "wikipediaSlug": "Claymore_(manga)",
    "image": "ClaymoreCoverTankobon1.jpg",
    "pageViews": 12110
  },
  {
    "qid": "Q392125",
    "title": "‘Tokyo Mew Mew’ begins",
    "subtitle": "Japanese manga series",
    "year": 2000,
    "fact": "Tokyo Mew Mew is a Japanese manga series created and illustrated by Mia Ikumi and written by Reiko Yoshida.",
    "wikipediaSlug": "Tokyo_Mew_Mew",
    "image": "Mewmew.jpg",
    "pageViews": 11832
  },
  {
    "qid": "Q723727",
    "title": "‘Sin City’ begins",
    "subtitle": "Comic books series by Frank Miller",
    "year": 1991,
    "fact": "Sin City is a series of neo-noir comics by American comic book writer-artist Frank Miller.",
    "wikipediaSlug": "Sin_City",
    "image": "Sin_City_Hard_Goodbye.jpg",
    "pageViews": 11630
  },
  {
    "qid": "Q221369",
    "title": "‘Chobits’ begins",
    "subtitle": "Japanese manga series",
    "year": 2000,
    "fact": "Chobits is a Japanese manga series written and illustrated by the Japanese manga collective Clamp.",
    "wikipediaSlug": "Chobits",
    "image": "Chobits_volume_1_cover.jpg",
    "pageViews": 11580
  },
  {
    "qid": "Q390279",
    "title": "‘Yotsuba&!’ begins",
    "subtitle": "Japanese manga series",
    "year": 2003,
    "fact": "Yotsuba&!",
    "wikipediaSlug": "Yotsuba%26!",
    "image": "Yotsuba&-vol1cover-jp.png",
    "pageViews": 10938
  },
  {
    "qid": "Q1799866",
    "title": "‘Detective Comics’ begins",
    "subtitle": "Title used for two American comic book series",
    "year": 1937,
    "fact": "Detective Comics is an American comic book series published by Detective Comics, later shortened to DC Comics.",
    "wikipediaSlug": "Detective_Comics",
    "image": "Detective_Comics_27_(May_1939).png",
    "pageViews": 10526
  },
  {
    "qid": "Q582763",
    "title": "‘Hikaru no Go’ begins",
    "subtitle": "Japanese manga series",
    "year": 1999,
    "fact": "Hikaru no Go is a Japanese manga series based on the board game Go, written by Yumi Hotta and illustrated by Takeshi Obata.",
    "wikipediaSlug": "Hikaru_no_Go",
    "image": "Hikaru_no_Go_1.png",
    "pageViews": 10387
  },
  {
    "qid": "Q501456",
    "title": "‘W.I.T.C.H.’ begins",
    "subtitle": "Italian fantasy comics series",
    "year": 2001,
    "fact": "W.I.T.C.H. is an Italian fantasy Disney comics series created by Elisabetta Gnone, Alessandro Barbucci, and Barbara Canepa.",
    "wikipediaSlug": "W.I.T.C.H.",
    "image": "WITCHposter.jpg",
    "pageViews": 10019
  },
  {
    "qid": "Q531298",
    "title": "‘Zatch Bell!’ begins",
    "subtitle": "Japanese manga series",
    "year": 2001,
    "fact": "Zatch Bell!, known in Japan as Konjiki no Gash!!, is a Japanese manga series written and illustrated by Makoto Raiku.",
    "wikipediaSlug": "Zatch_Bell!",
    "image": "Gash_Bel.png",
    "pageViews": 9875
  },
  {
    "qid": "Q862850",
    "title": "‘Reborn!’ begins",
    "subtitle": "Japanese manga series",
    "year": 2004,
    "fact": "Reborn!, known in Japan as Katekyō Hitman Reborn!",
    "wikipediaSlug": "Reborn!",
    "image": "Katekyohitmanrebornvolumetwenty.png",
    "pageViews": 9616
  },
  {
    "qid": "Q11611205",
    "title": "‘A Silent Voice’ begins",
    "subtitle": "Japanese manga series",
    "year": 2013,
    "fact": "A Silent Voice is a Japanese manga series written and illustrated by Yoshitoki Ōima.",
    "wikipediaSlug": "A_Silent_Voice_(manga)",
    "image": "Koe_no_Katachi,_Volume_1.jpg",
    "pageViews": 9498
  },
  {
    "qid": "Q270595",
    "title": "‘Vampire Knight’ begins",
    "subtitle": "Japanese manga series",
    "year": 2004,
    "fact": "Vampire Knight is a Japanese manga series written by Matsuri Hino.",
    "wikipediaSlug": "Vampire_Knight",
    "image": "Vampire_Knight,_Volume_1.jpg",
    "pageViews": 9240
  },
  {
    "qid": "Q696210",
    "title": "‘Fushigi Yûgi’ begins",
    "subtitle": "Japanese manga series",
    "year": 1991,
    "fact": "Fushigi Yûgi, also known as Fushigi Yûgi: The Mysterious Play or Curious Play, is a Japanese manga series written and illustrated by Yuu Watase.",
    "wikipediaSlug": "Fushigi_Y%C3%BBgi",
    "image": "Fushigi_Yugi,_Japanese_Volume_1.jpg",
    "pageViews": 8787
  },
  {
    "qid": "Q804555",
    "title": "‘Bakuman’ begins",
    "subtitle": "Japanese manga series",
    "year": 2008,
    "fact": "Bakuman is a Japanese manga series written by Tsugumi Ohba and illustrated by Takeshi Obata, the same creative team responsible for Death Note.",
    "wikipediaSlug": "Bakuman",
    "image": "Bakuman_Vol_1_Cover.jpg",
    "pageViews": 8607
  },
  {
    "qid": "Q862351",
    "title": "‘Maison Ikkoku’ begins",
    "subtitle": "Japanese manga series",
    "year": 1980,
    "fact": "Maison Ikkoku is a Japanese manga series written and illustrated by Rumiko Takahashi.",
    "wikipediaSlug": "Maison_Ikkoku",
    "image": "Maison_Ikkoku_Volume_1.jpg",
    "pageViews": 8490
  },
  {
    "qid": "Q275953",
    "title": "‘Mermaid Melody Pichi Pichi Pitch’ begins",
    "subtitle": "Japanese manga series",
    "year": 2002,
    "fact": "Pichi Pichi Pitch is a Japanese manga series created and illustrated by Pink Hanamori and written by Michiko Yokote.",
    "wikipediaSlug": "Mermaid_Melody_Pichi_Pichi_Pitch",
    "image": "Pichi_Pichi_Pitch_manga_vol_1.jpg",
    "pageViews": 8458
  },
  {
    "qid": "Q95063",
    "title": "‘Planetes’ begins",
    "subtitle": "Japanese manga series",
    "year": 2001,
    "fact": "Planetes is a Japanese hard science fiction manga written and illustrated by Makoto Yukimura.",
    "wikipediaSlug": "Planetes",
    "image": "Planetes_manga_vol_1.jpg",
    "pageViews": 8395
  },
  {
    "qid": "Q322613",
    "title": "‘Love Hina’ begins",
    "subtitle": "Japanese manga series",
    "year": 1998,
    "fact": "Love Hina is a Japanese manga series written and illustrated by Ken Akamatsu.",
    "wikipediaSlug": "Love_Hina",
    "image": "Love_Hina_volume_1.jpg",
    "pageViews": 8357
  },
  {
    "qid": "Q706167",
    "title": "‘The Prince of Tennis’ begins",
    "subtitle": "Japanese manga series",
    "year": 1999,
    "fact": "The Prince of Tennis is a Japanese manga series written and illustrated by Takeshi Konomi.",
    "wikipediaSlug": "The_Prince_of_Tennis",
    "image": "Prince_of_Tennis_Volume_01.JPG",
    "pageViews": 7573
  },
  {
    "qid": "Q582630",
    "title": "‘Sgt. Frog’ begins",
    "subtitle": "Japanese manga series",
    "year": 1999,
    "fact": "Sgt.",
    "wikipediaSlug": "Sgt._Frog",
    "image": "Kerorotankobon1.jpg",
    "pageViews": 7318
  },
  {
    "qid": "Q467681",
    "title": "‘Oh My Goddess!’ begins",
    "subtitle": "Japanese manga series",
    "year": 1988,
    "fact": "Oh My Goddess!, or Ah!",
    "wikipediaSlug": "Oh_My_Goddess!",
    "image": "Oh_My_Goddess_Manga_cover.jpg",
    "pageViews": 7243
  },
  {
    "qid": "Q12116",
    "title": "‘Corto Maltese’ begins",
    "subtitle": "Comics series",
    "year": 1967,
    "fact": "Corto Maltese is a series of adventure comics following the eponymous protagonist, an adventurous sailor.",
    "wikipediaSlug": "Corto_Maltese",
    "image": "Corto_Maltese-comics_series.png",
    "pageViews": 7217
  },
  {
    "qid": "Q1813828",
    "title": "‘Oruchuban Ebichu’ begins",
    "subtitle": "Japanese manga series",
    "year": 1990,
    "fact": "Oruchuban Ebichu (おるちゅばんエビちゅ) is a Japanese manga series by Risa Itō that was published by Futabasha Publishers.",
    "wikipediaSlug": "Oruchuban_Ebichu",
    "image": "EbichuDVD.jpg",
    "pageViews": 6198
  },
  {
    "qid": "Q642944",
    "title": "‘Negima! Magister Negi Magi’ begins",
    "subtitle": "Japanese manga series",
    "year": 2003,
    "fact": "Negima!",
    "wikipediaSlug": "Negima!_Magister_Negi_Magi",
    "image": "Negima!_Magister_Negi_Magi_1.png",
    "pageViews": 5666
  },
  {
    "qid": "Q1046959",
    "title": "‘Nodame Cantabile’ begins",
    "subtitle": "Japanese manga series",
    "year": 2001,
    "fact": "Nodame Cantabile is a Japanese manga series written and illustrated by Tomoko Ninomiya.",
    "wikipediaSlug": "Nodame_Cantabile",
    "image": "Nodame_Cantabile_Vol.1_cover.jpg",
    "pageViews": 5417
  },
  {
    "qid": "Q113329",
    "title": "‘Magic Kaito’ begins",
    "subtitle": "Japanese manga series",
    "year": 1987,
    "fact": "Magic Kaito is a Japanese manga series written and illustrated by Gosho Aoyama.",
    "wikipediaSlug": "Magic_Kaito",
    "image": "MagicKaito1.jpg",
    "pageViews": 4732
  },
  {
    "qid": "Q137308",
    "title": "‘Blueberry’ begins",
    "subtitle": "Comic book series",
    "year": 1963,
    "fact": "Blueberry is a Western comic series created in the Franco-Belgian bandes dessinées (BD) tradition by the Belgian scriptwriter Jean-Michel Charlier and French comics artist Jean \"Mœbius\" Giraud.",
    "wikipediaSlug": "Blueberry_(comics)",
    "image": "Blueberry_Giraud.png",
    "pageViews": 4577
  },
  {
    "qid": "Q482472",
    "title": "‘School Rumble’ begins",
    "subtitle": "Japanese manga series",
    "year": 2002,
    "fact": "School Rumble is a Japanese manga series written and illustrated by Jin Kobayashi.",
    "wikipediaSlug": "School_Rumble",
    "image": "School_Rumble_13.png",
    "pageViews": 4082
  },
  {
    "qid": "Q282464",
    "title": "‘Basilisk’ begins",
    "subtitle": "Japanese manga series",
    "year": 2003,
    "fact": "Basilisk is a Japanese manga series by Masaki Segawa, based on Futaro Yamada's 1958 novel The Kouga Ninja Scrolls.",
    "wikipediaSlug": "Basilisk_(manga)",
    "image": "Basilisk_vol1_cover.jpg",
    "pageViews": 3548
  },
  {
    "qid": "Q737153",
    "title": "‘Gaston’ begins",
    "subtitle": "Comic strip series",
    "year": 1957,
    "fact": "Gaston is a Belgian gag-a-day comic strip created in 1957 by the Belgian cartoonist André Franquin in the Franco-Belgian comics magazine Spirou.",
    "wikipediaSlug": "Gaston_(comics)",
    "image": "Gaston_Lagaffe-comics_series.png",
    "pageViews": 3057
  },
  {
    "qid": "Q1130014",
    "title": "‘Spirou et Fantasio in « Le Journal de Spirou »’ begins",
    "subtitle": "Franco-Belgian comics series",
    "year": 1938,
    "fact": "Spirou & Fantasio, commonly shortened to Spirou, is one of the most popular classic Franco-Belgian comics.",
    "wikipediaSlug": "Spirou_%26_Fantasio",
    "image": "Spirou-ensemble1.jpg",
    "pageViews": 3054
  }
]
