{
  "data": [
    {
      "name": "Email",
      "slug": "email",
      "ecv": 0.00246181262,
      "footprint": 0.00246181262,
      "footprintDetail": [
        {
          "value": 0.001286218,
          "id": 13
        },
        {
          "value": 0.00008684837,
          "id": 14
        },
        {
          "value": 0.00003580927,
          "id": 15
        },
        {
          "value": 0.00093525547,
          "id": 16
        },
        {
          "value": 0.00011768151,
          "id": 17
        }
      ]
    },
    {
      "name": "Spam",
      "slug": "spam",
      "ecv": 0.00373863698,
      "footprint": 0.00373863698,
      "footprintDetail": [
        {
          "value": 0.0026857,
          "id": 15
        },
        {
          "value": 0.00093525547,
          "id": 16
        },
        {
          "value": 0.00011768151,
          "id": 17
        }
      ]
    },
    {
      "name": "Store 1 GB of data",
      "slug": "stockagedonnee",
      "ecv": 0.00023533417,
      "footprint": 0.00023533417,
      "footprintDetail": [
        {
          "value": 0.00012454537,
          "id": 16
        },
        {
          "value": 0.0001107888,
          "id": 17
        }
      ]
    },
    {
      "name": "Web search",
      "slug": "rechercheweb",
      "ecv": 0.051042269652307,
      "footprint": 0.051042269652307,
      "footprintDetail": [
        {
          "value": 0.0007446526,
          "id": 13
        },
        {
          "value": 0.0502806333,
          "id": 14
        },
        {
          "value": 0.00000141881,
          "id": 15
        },
        {
          "value": 2.0842307e-8,
          "id": 16
        },
        {
          "value": 0.0000155441,
          "id": 17
        }
      ]
    },
    {
      "name": "Video streaming",
      "slug": "streamingvideo",
      "ecv": 0.06401675291000002,
      "footprint": 0.06401675291000002,
      "footprintDetail": [
        {
          "value": 0.0327361035,
          "id": 13
        },
        {
          "value": 0.002903607,
          "id": 14
        },
        {
          "value": 0.02780804,
          "id": 15
        },
        {
          "value": 0.000236636,
          "id": 16
        },
        {
          "value": 0.00033236641,
          "id": 17
        }
      ]
    },
    {
      "name": "Video conferencing",
      "slug": "visioconference",
      "ecv": 0.05706336546216,
      "footprint": 0.05706336546216,
      "footprintDetail": [
        {
          "value": 0.04100456621,
          "id": 13
        },
        {
          "value": 0.002845,
          "id": 14
        },
        {
          "value": 0.0129770857,
          "id": 15
        },
        {
          "value": 0.000236636,
          "id": 16
        },
        {
          "value": 7.755216e-8,
          "id": 17
        }
      ]
    },
    {
      "name": "GB of data",
      "slug": "telechargement",
      "ecv": 0.00950468087,
      "footprint": 0.00950468087,
      "footprintDetail": [
        {
          "value": 0.0092693467,
          "id": 15
        },
        {
          "value": 0.00012454537,
          "id": 16
        },
        {
          "value": 0.0001107888,
          "id": 17
        }
      ]
    }
  ]
}