[
  {
    "item": "http://www.wikidata.org/entity/Q235080",
    "itemLabel": "Alfonso VI of León and Castile",
    "positionLabel": "Monarch of the Kingdom of León",
    "sexLabel": "male",
    "year": "1065",
    "sitelinks": "48"
  },
  {
    "item": "http://www.wikidata.org/entity/Q312767",
    "itemLabel": "Alfonso VII of Castile",
    "positionLabel": "Monarch of the Kingdom of León",
    "sexLabel": "male",
    "year": "1126",
    "sitelinks": "43"
  },
  {
    "item": "http://www.wikidata.org/entity/Q317905",
    "itemLabel": "Sancho II of León and Castile",
    "positionLabel": "Monarch of the Kingdom of León",
    "sexLabel": "male",
    "year": "1071",
    "sitelinks": "41"
  },
  {
    "item": "http://www.wikidata.org/entity/Q128701",
    "itemLabel": "Urraca of León",
    "positionLabel": "Monarch of the Kingdom of León",
    "sexLabel": "female",
    "year": "1109",
    "sitelinks": "40"
  },
  {
    "item": "http://www.wikidata.org/entity/Q283561",
    "itemLabel": "Alfonso V of León",
    "positionLabel": "Monarch of the Kingdom of León",
    "sexLabel": "male",
    "year": "999",
    "sitelinks": "36"
  },
  {
    "item": "http://www.wikidata.org/entity/Q316768",
    "itemLabel": "Ferdinand II of León",
    "positionLabel": "Monarch of the Kingdom of León",
    "sexLabel": "male",
    "year": "1157",
    "sitelinks": "36"
  },
  {
    "item": "http://www.wikidata.org/entity/Q333676",
    "itemLabel": "Ordoño II of León",
    "positionLabel": "Monarch of the Kingdom of León",
    "sexLabel": "male",
    "year": "914",
    "sitelinks": "36"
  },
  {
    "item": "http://www.wikidata.org/entity/Q225113",
    "itemLabel": "Ramiro II of León",
    "positionLabel": "Monarch of the Kingdom of León",
    "sexLabel": "male",
    "year": "931",
    "sitelinks": "34"
  },
  {
    "item": "http://www.wikidata.org/entity/Q333699",
    "itemLabel": "García I of León",
    "positionLabel": "Monarch of the Kingdom of León",
    "sexLabel": "male",
    "year": "910",
    "sitelinks": "34"
  },
  {
    "item": "http://www.wikidata.org/entity/Q264836",
    "itemLabel": "Alfonso IV of León",
    "positionLabel": "Monarch of the Kingdom of León",
    "sexLabel": "male",
    "year": "926",
    "sitelinks": "33"
  },
  {
    "item": "http://www.wikidata.org/entity/Q333603",
    "itemLabel": "Fruela II of Asturias",
    "positionLabel": "Monarch of the Kingdom of León",
    "sexLabel": "male",
    "year": "924",
    "sitelinks": "33"
  },
  {
    "item": "http://www.wikidata.org/entity/Q345392",
    "itemLabel": "Bermudo III of León",
    "positionLabel": "Monarch of the Kingdom of León",
    "sexLabel": "male",
    "year": "1028",
    "sitelinks": "31"
  },
  {
    "item": "http://www.wikidata.org/entity/Q333627",
    "itemLabel": "Ordoño III of León",
    "positionLabel": "Monarch of the Kingdom of León",
    "sexLabel": "male",
    "year": "951",
    "sitelinks": "31"
  },
  {
    "item": "http://www.wikidata.org/entity/Q342520",
    "itemLabel": "Bermudo II of León",
    "positionLabel": "Monarch of the Kingdom of León",
    "sexLabel": "male",
    "year": "985",
    "sitelinks": "30"
  },
  {
    "item": "http://www.wikidata.org/entity/Q1847459",
    "itemLabel": "Sancha of León",
    "positionLabel": "Monarch of the Kingdom of León",
    "sexLabel": "female",
    "year": "1037",
    "sitelinks": "29"
  },
  {
    "item": "http://www.wikidata.org/entity/Q452053",
    "itemLabel": "Alfonso Fróilaz",
    "positionLabel": "Monarch of the Kingdom of León",
    "sexLabel": "male",
    "year": "925",
    "sitelinks": "21"
  },
  {
    "item": "http://www.wikidata.org/entity/Q840414",
    "itemLabel": "Elvira Menendez",
    "positionLabel": "Monarch of the Kingdom of León",
    "sexLabel": "female",
    "year": "914",
    "sitelinks": "12"
  }
]
